LICENSE
MANIFEST.in
README.md
setup.py
depot_pm/__init__.py
depot_pm/check.py
depot_pm/configuration.py
depot_pm/installer.py
depot_pm/main.py
depot_pm/package.py
depot_pm.egg-info/PKG-INFO
depot_pm.egg-info/SOURCES.txt
depot_pm.egg-info/dependency_links.txt
depot_pm.egg-info/entry_points.txt
depot_pm.egg-info/requires.txt
depot_pm.egg-info/top_level.txt